<?xml version="1.0" encoding="UTF-8" ?>
<!-- Version 1.0 by Terry O'Brien -->
<characterSet name="Ogham" type="Languages" description="Ogham Runes" >
    <characterSetResource>http://en.wikipedia.org/wiki/Ogham</characterSetResource>
    <characterSetRange>x01680 - x0169F</characterSetRange>

    <characterSubset name="Aicme Ailme" >
        <characterSubsetArray>
            <characterDefinition character="&amp;#5776;">Ogham Letter Ailm</characterDefinition>
            <characterDefinition character="&amp;#5777;">Ogham Letter Onn</characterDefinition>
            <characterDefinition character="&amp;#5778;">Ogham Letter Ur</characterDefinition>
            <characterDefinition character="&amp;#5779;">Ogham Letter Eadhadh</characterDefinition>
            <characterDefinition character="&amp;#5780;">Ogham Letter Iodhadh</characterDefinition>
        </characterSubsetArray>
    </characterSubset>
    <characterSubset name="Aicme Beithe" >
        <characterSubsetArray>
            <characterDefinition character="&amp;#5761;">Ogham Letter Beith</characterDefinition>
            <characterDefinition character="&amp;#5762;">Ogham Letter Luis</characterDefinition>
            <characterDefinition character="&amp;#5763;">Ogham Letter Fearn</characterDefinition>
            <characterDefinition character="&amp;#5764;">Ogham Letter Sail</characterDefinition>
            <characterDefinition character="&amp;#5765;">Ogham Letter Nion</characterDefinition>
        </characterSubsetArray>
    </characterSubset>
    <characterSubset name="Aicme hUatha" >
        <characterSubsetArray>
            <characterDefinition character="&amp;#5766;">Ogham Letter Uath</characterDefinition>
            <characterDefinition character="&amp;#5767;">Ogham Letter Dair</characterDefinition>
            <characterDefinition character="&amp;#5768;">Ogham Letter Tinne</characterDefinition>
            <characterDefinition character="&amp;#5769;">Ogham Letter Coll</characterDefinition>
            <characterDefinition character="&amp;#5770;">Ogham Letter Ceirt</characterDefinition>
        </characterSubsetArray>
    </characterSubset>
    <characterSubset name="Aicme Muine" >
        <characterSubsetArray>
            <characterDefinition character="&amp;#5771;">Ogham Letter Muin</characterDefinition>
            <characterDefinition character="&amp;#5772;">Ogham Letter Gort</characterDefinition>
            <characterDefinition character="&amp;#5773;">Ogham Letter Ngeadal</characterDefinition>
            <characterDefinition character="&amp;#5774;">Ogham Letter Straif</characterDefinition>
            <characterDefinition character="&amp;#5775;">Ogham Letter Ruis</characterDefinition>
        </characterSubsetArray>
    </characterSubset>
    <characterSubset name="Forfeda" >
        <characterSubsetArray>
            <characterDefinition character="&amp;#5781;">Ogham Letter Eabhadh</characterDefinition>
            <characterDefinition character="&amp;#5782;">Ogham Letter Or</characterDefinition>
            <characterDefinition character="&amp;#5783;">Ogham Letter Uilleann</characterDefinition>
            <characterDefinition character="&amp;#5784;">Ogham Letter Ifin</characterDefinition>
            <characterDefinition character="&amp;#5785;">Ogham Letter Eamhancholl</characterDefinition>
            <characterDefinition character="&amp;#5786;">Ogham Letter Peith</characterDefinition>
        </characterSubsetArray>
    </characterSubset>
    <characterSubset name="Miscellaneous" >
        <characterSubsetArray>
            <characterDefinition character="&amp;#5760;">Ogham Space Mark</characterDefinition>
            <characterDefinition character="&amp;#5787;">Ogham Feather Mark</characterDefinition>
            <characterDefinition character="&amp;#5788;">Ogham Reversed Feather Mark</characterDefinition>
        </characterSubsetArray>
    </characterSubset>
</characterSet>