<?xml version="1.0" encoding="UTF-8" ?>
<!-- Version 1.0 by Terry O'Brien -->
<characterSet name="Runic" type="Languages" description="Runic (Futhark) Symbols" >
    <characterSetResource>http://www.unicode.org/charts/PDF/U16A0.pdf</characterSetResource>
    <characterSetRange>x016A0 - x016FF</characterSetRange>

    <characterSubset name="Letters" >
        <characterSubsetArray>
            <characterDefinition character="&amp;#5792;">Runic Letter Fehu Feoh Fe F</characterDefinition>
            <characterDefinition character="&amp;#5793;">Runic Letter V</characterDefinition>
            <characterDefinition character="&amp;#5794;">Runic Letter Uruz Ur U</characterDefinition>
            <characterDefinition character="&amp;#5795;">Runic Letter Yr</characterDefinition>
            <characterDefinition character="&amp;#5796;">Runic Letter Y</characterDefinition>
            <characterDefinition character="&amp;#5797;">Runic Letter W</characterDefinition>
            <characterDefinition character="&amp;#5798;">Runic Letter Thurisaz Thurs Thorn</characterDefinition>
            <characterDefinition character="&amp;#5799;">Runic Letter Eth</characterDefinition>
            <characterDefinition character="&amp;#5800;">Runic Letter Ansuz A</characterDefinition>
            <characterDefinition character="&amp;#5801;">Runic Letter Os o</characterDefinition>
            <characterDefinition character="&amp;#5802;">Runic Letter Ac a</characterDefinition>
            <characterDefinition character="&amp;#5803;">Runic Letter Aesc</characterDefinition>
            <characterDefinition character="&amp;#5804;">Runic Letter Long-branch-oss O</characterDefinition>
            <characterDefinition character="&amp;#5805;">Runic Letter Short-twig-oss O</characterDefinition>
            <characterDefinition character="&amp;#5806;">Runic Letter O</characterDefinition>
            <characterDefinition character="&amp;#5807;">Runic Letter Oe</characterDefinition>
        </characterSubsetArray>
        <characterSubsetArray>
            <characterDefinition character="&amp;#5808;">Runic Letter On</characterDefinition>
            <characterDefinition character="&amp;#5809;">Runic Letter Raido Rad Reid R</characterDefinition>
            <characterDefinition character="&amp;#5810;">Runic Letter Kauna</characterDefinition>
            <characterDefinition character="&amp;#5811;">Runic Letter Cen</characterDefinition>
            <characterDefinition character="&amp;#5812;">Runic Letter Kaun k</characterDefinition>
            <characterDefinition character="&amp;#5813;">Runic Letter G</characterDefinition>
            <characterDefinition character="&amp;#5814;">Runic Letter Eng</characterDefinition>
            <characterDefinition character="&amp;#5815;">Runic Letter Gebo Gyfu G</characterDefinition>
            <characterDefinition character="&amp;#5816;">Runic Letter Gar</characterDefinition>
            <characterDefinition character="&amp;#5817;">Runic Letter Wunjo Wynn W</characterDefinition>
            <characterDefinition character="&amp;#5818;">Runic Letter Haglaz H</characterDefinition>
            <characterDefinition character="&amp;#5819;">Runic Letter Haegl H</characterDefinition>
            <characterDefinition character="&amp;#5820;">Runic Letter Long-branch-hagall H</characterDefinition>
            <characterDefinition character="&amp;#5821;">Runic Letter Short-twig-hagall H</characterDefinition>
            <characterDefinition character="&amp;#5822;">Runic Letter Naudiz Nyd Naud N</characterDefinition>
            <characterDefinition character="&amp;#5823;">Runic Letter Short-twig-naud N</characterDefinition>
        </characterSubsetArray>
        <characterSubsetArray>
            <characterDefinition character="&amp;#5824;">Runic Letter Dotted-n</characterDefinition>
            <characterDefinition character="&amp;#5825;">Runic Letter Isaz Is Iss I</characterDefinition>
            <characterDefinition character="&amp;#5826;">Runic Letter E</characterDefinition>
            <characterDefinition character="&amp;#5827;">Runic Letter Jeran J</characterDefinition>
            <characterDefinition character="&amp;#5828;">Runic Letter Ger</characterDefinition>
            <characterDefinition character="&amp;#5829;">Runic Letter Long-branch-ar Ae</characterDefinition>
            <characterDefinition character="&amp;#5830;">Runic Letter Short-twig-ar A</characterDefinition>
            <characterDefinition character="&amp;#5831;">Runic Letter Iwaz Eoh</characterDefinition>
            <characterDefinition character="&amp;#5832;">Runic Letter Pertho Peorth P</characterDefinition>
            <characterDefinition character="&amp;#5833;">Runic Letter Algiz Eolhx</characterDefinition>
            <characterDefinition character="&amp;#5834;">Runic Letter Sowilo A</characterDefinition>
            <characterDefinition character="&amp;#5835;">Runic Letter Sigel Long-branch-sol S</characterDefinition>
            <characterDefinition character="&amp;#5836;">Runic Letter Short-twig-sol S</characterDefinition>
            <characterDefinition character="&amp;#5837;">Runic Letter C</characterDefinition>
            <characterDefinition character="&amp;#5838;">Runic Letter Z</characterDefinition>
            <characterDefinition character="&amp;#5839;">Runic Letter Tiwaz Tir Tyr T</characterDefinition>
        </characterSubsetArray>
        <characterSubsetArray>
            <characterDefinition character="&amp;#5840;">Runic Letter Short-twig-tyr T</characterDefinition>
            <characterDefinition character="&amp;#5841;">Runic Letter D</characterDefinition>
            <characterDefinition character="&amp;#5842;">Runic Letter Berkanan Beorc Bjarkan B</characterDefinition>
            <characterDefinition character="&amp;#5843;">Runic Letter Short-twig-bjarkan B</characterDefinition>
            <characterDefinition character="&amp;#5844;">Runic Letter Dotted-p</characterDefinition>
            <characterDefinition character="&amp;#5845;">Runic Letter Open-p</characterDefinition>
            <characterDefinition character="&amp;#5846;">Runic Letter Ehwaz Eh E</characterDefinition>
            <characterDefinition character="&amp;#5847;">Runic Letter Mannaz Man M</characterDefinition>
            <characterDefinition character="&amp;#5848;">Runic Letter Long-branch-madr M</characterDefinition>
            <characterDefinition character="&amp;#5849;">Runic Letter Short-twig-madr M</characterDefinition>
            <characterDefinition character="&amp;#5850;">Runic Letter Laukaz Lagu Logr L</characterDefinition>
            <characterDefinition character="&amp;#5851;">Runic Letter Dotted-l</characterDefinition>
            <characterDefinition character="&amp;#5852;">Runic Letter Ingwaz</characterDefinition>
            <characterDefinition character="&amp;#5853;">Runic Letter Ing</characterDefinition>
            <characterDefinition character="&amp;#5854;">Runic Letter Dagaz Daeg D</characterDefinition>
            <characterDefinition character="&amp;#5855;">Runic Letter Othalan Ethel O</characterDefinition>
        </characterSubsetArray>
        <characterSubsetArray>
            <characterDefinition character="&amp;#5856;">Runic Letter Ear</characterDefinition>
            <characterDefinition character="&amp;#5857;">Runic Letter Ior</characterDefinition>
            <characterDefinition character="&amp;#5858;">Runic Letter Cweorth</characterDefinition>
            <characterDefinition character="&amp;#5859;">Runic Letter Calc</characterDefinition>
            <characterDefinition character="&amp;#5860;">Runic Letter Cealc</characterDefinition>
            <characterDefinition character="&amp;#5861;">Runic Letter Stan</characterDefinition>
            <characterDefinition character="&amp;#5862;">Runic Letter Long-branch-yr</characterDefinition>
            <characterDefinition character="&amp;#5863;">Runic Letter Short-twig-yr</characterDefinition>
            <characterDefinition character="&amp;#5864;">Runic Letter Icelandic-yr</characterDefinition>
            <characterDefinition character="&amp;#5865;">Runic Letter Q</characterDefinition>
            <characterDefinition character="&amp;#5866;">Runic Letter X</characterDefinition>
        </characterSubsetArray>
    </characterSubset>
    <characterSubset name="Punctuation" >
        <characterSubsetArray>
            <characterDefinition character="&amp;#5867;">Runic Single Punctuation</characterDefinition>
            <characterDefinition character="&amp;#5868;">Runic Multiple Punctuation</characterDefinition>
            <characterDefinition character="&amp;#5869;">Runic Cross Punctuation</characterDefinition>
            <characterDefinition character="&amp;#5870;">Runic Arlaug Symbol</characterDefinition>
            <characterDefinition character="&amp;#5871;">Runic Tvimadur Symbol</characterDefinition>
            <characterDefinition character="&amp;#5872;">Runic Belgthor Symbol</characterDefinition>
        </characterSubsetArray>
    </characterSubset>
</characterSet>
